indexia/__init__.py
indexia/eidola.py
indexia/indexia.py
indexia/inquiry.py
indexia/py.typed
indexia/schemata.py
indexia-1.0.3.dist-info/licenses/LICENSE.rst
indexia-1.0.3.dist-info/METADATA
indexia-1.0.3.dist-info/WHEEL
indexia-1.0.3.dist-info/top_level.txt
indexia-1.0.3.dist-info/RECORD
