Metadata-Version: 2.4
Name: indexia
Version: 1.0.3
Summary: Collections & connections. A virtual Zettelkasten.
Home-page: https://github.com/Perceptua/indexia
Author: Aphorikles
Author-email: Aphorikles <perceptua.blue@gmail.com>
License: MIT
Project-URL: Homepage, https://github.com/Perceptua/indexia
Project-URL: Bugs, https://github.com/Perceptua/indexia/issues
Project-URL: Documentation, https://indexia.readthedocs.io/en/latest/
Keywords: Zettelkasten,knowledge-tree,notes,annotation,XML
Classifier: Programming Language :: Python :: 3
Classifier: License :: OSI Approved :: MIT License
Classifier: Operating System :: OS Independent
Requires-Python: >=3.8
License-File: LICENSE.rst
Requires-Dist: networkx
Requires-Dist: pandas
Requires-Dist: pyvis
Dynamic: license-file
